datadog_deployer/__init__.py
datadog_deployer/config.py
datadog_deployer/deployer.py
datadog_deployer/dumper.py
datadog_deployer/main.py
datadog_deployer/monitor.py
datadog_deployer/query_metric.py
datadog_deployer-0.4.0.dist-info/licenses/LICENSE
datadog_deployer-0.4.0.dist-info/METADATA
datadog_deployer-0.4.0.dist-info/WHEEL
datadog_deployer-0.4.0.dist-info/entry_points.txt
datadog_deployer-0.4.0.dist-info/top_level.txt
datadog_deployer-0.4.0.dist-info/RECORD
