Metadata-Version: 2.4
Name: datadog-deployer
Version: 0.4.0
Summary: Deployment of datadog monitors.
Home-page: https://github.com/binxio/datadog-deployer
Author: Mark van Holsteijn
Author-email: mvanholsteijn@xebia.com
Platform: any
License-File: LICENSE
Requires-Dist: ruamel.yaml
Requires-Dist: click
Requires-Dist: datadog
Dynamic: author
Dynamic: author-email
Dynamic: description
Dynamic: home-page
Dynamic: license-file
Dynamic: platform
Dynamic: requires-dist
Dynamic: summary
